package/__init__.py
package/main.py
opengithub_web-0.0.3.dist-info/LICENSE
opengithub_web-0.0.3.dist-info/METADATA
opengithub_web-0.0.3.dist-info/WHEEL
opengithub_web-0.0.3.dist-info/top_level.txt
opengithub_web-0.0.3.dist-info/RECORD
