Metadata-Version: 2.1
Name: opengithub-web
Version: 0.0.3
Summary: © 2022 by Ezozbek Kholbutayev
Home-page: https://github.com/pypa/sampleproject
Author: Ezozbek kholbutayev
Author-email: ezozbekh8@gmail.com
Project-URL: Bug Tracker, https://github.com/pypa/sampleproject/issues
Classifier: Programming Language :: Python :: 3
Classifier: License :: OSI Approved :: MIT License
Classifier: Operating System :: OS Independent
Requires-Python: >=3.6
License-File: LICENSE
